yakup_hello_module/__init__.py
yakup_hello_module/yakup_hello_module.py
yakup_hello_module-1.0.4.dist-info/LICENSE.txt
yakup_hello_module-1.0.4.dist-info/METADATA
yakup_hello_module-1.0.4.dist-info/WHEEL
yakup_hello_module-1.0.4.dist-info/top_level.txt
yakup_hello_module-1.0.4.dist-info/RECORD
