Metadata-Version: 2.1
Name: yakup-hello-module
Version: 1.0.4
Summary: Hello print eder.
Home-page: UNKNOWN
Author: Yakup Demirtaş
Author-email: yakup.demirtas@metu.edu.tr
License: UNKNOWN
Platform: UNKNOWN
